{"nodes": [{"id": "home_soic_project_spacetrek_pkg_exception_exception_go", "label": "exception.go", "file_type": "code", "source_file": "pkg/exception/exception.go", "source_location": "L1"}, {"id": "exception_apperror", "label": "AppError", "file_type": "code", "source_file": "pkg/exception/exception.go", "source_location": "L9"}, {"id": "fielderror", "label": "FieldError", "file_type": "code", "source_file": "pkg/exception/exception.go", "source_location": "L13"}, {"id": "exception_apperror_error", "label": ".Error()", "file_type": "code", "source_file": "pkg/exception/exception.go", "source_location": "L18"}, {"id": "exception_apperror_unwrap", "label": ".Unwrap()", "file_type": "code", "source_file": "pkg/exception/exception.go", "source_location": "L26"}, {"id": "exception_exception_new", "label": "New()", "file_type": "code", "source_file": "pkg/exception/exception.go", "source_location": "L31"}, {"id": "exception_exception_wrap", "label": "Wrap()", "file_type": "code", "source_file": "pkg/exception/exception.go", "source_location": "L40"}, {"id": "exception_exception_fromerror", "label": "FromError()", "file_type": "code", "source_file": "pkg/exception/exception.go", "source_location": "L52"}], "edges": [{"source": "home_soic_project_spacetrek_pkg_exception_exception_go", "target": "go_pkg_errors", "relation": "imports_from", "confidence": "EXTRACTED", "source_file": "pkg/exception/exception.go", "source_location": "L4", "weight": 1.0, "context": "import"}, {"source": "home_soic_project_spacetrek_pkg_exception_exception_go", "target": "go_pkg_fmt", "relation": "imports_from", "confidence": "EXTRACTED", "source_file": "pkg/exception/exception.go", "source_location": "L5", "weight": 1.0, "context": "import"}, {"source": "home_soic_project_spacetrek_pkg_exception_exception_go", "target": "exception_apperror", "relation": "contains", "confidence": "EXTRACTED", "source_file": "pkg/exception/exception.go", "source_location": "L9", "weight": 1.0}, {"source": "exception_apperror", "target": "fielderror", "relation": "references", "confidence": "EXTRACTED", "source_file": "pkg/exception/exception.go", "source_location": "L13", "weight": 1.0, "context": "field"}, {"source": "exception_apperror", "target": "exception_apperror_error", "relation": "method", "confidence": "EXTRACTED", "source_file": "pkg/exception/exception.go", "source_location": "L18", "weight": 1.0}, {"source": "exception_apperror", "target": "exception_apperror_unwrap", "relation": "method", "confidence": "EXTRACTED", "source_file": "pkg/exception/exception.go", "source_location": "L26", "weight": 1.0}, {"source": "home_soic_project_spacetrek_pkg_exception_exception_go", "target": "exception_exception_new", "relation": "contains", "confidence": "EXTRACTED", "source_file": "pkg/exception/exception.go", "source_location": "L31", "weight": 1.0}, {"source": "exception_exception_new", "target": "exception_apperror", "relation": "references", "confidence": "EXTRACTED", "source_file": "pkg/exception/exception.go", "source_location": "L31", "weight": 1.0, "context": "return_type"}, {"source": "home_soic_project_spacetrek_pkg_exception_exception_go", "target": "exception_exception_wrap", "relation": "contains", "confidence": "EXTRACTED", "source_file": "pkg/exception/exception.go", "source_location": "L40", "weight": 1.0}, {"source": "exception_exception_wrap", "target": "exception_apperror", "relation": "references", "confidence": "EXTRACTED", "source_file": "pkg/exception/exception.go", "source_location": "L40", "weight": 1.0, "context": "return_type"}, {"source": "home_soic_project_spacetrek_pkg_exception_exception_go", "target": "exception_exception_fromerror", "relation": "contains", "confidence": "EXTRACTED", "source_file": "pkg/exception/exception.go", "source_location": "L52", "weight": 1.0}, {"source": "exception_exception_fromerror", "target": "exception_apperror", "relation": "references", "confidence": "EXTRACTED", "source_file": "pkg/exception/exception.go", "source_location": "L52", "weight": 1.0, "context": "return_type"}], "raw_calls": [{"caller_nid": "exception_apperror_error", "callee": "Sprintf", "is_member_call": false, "source_file": "/home/soic/project/spacetrek/pkg/exception/exception.go", "source_location": "L20"}, {"caller_nid": "exception_exception_fromerror", "callee": "As", "is_member_call": false, "source_file": "/home/soic/project/spacetrek/pkg/exception/exception.go", "source_location": "L57"}, {"caller_nid": "exception_exception_fromerror", "callee": "Internal", "is_member_call": false, "source_file": "/home/soic/project/spacetrek/pkg/exception/exception.go", "source_location": "L60"}]}