{"nodes": [{"id": "home_soic_project_spacetrek_src_repository_memory_agent_go", "label": "agent.go", "file_type": "code", "source_file": "src/repository/memory/agent.go", "source_location": "L1"}, {"id": "memory_agentrepository", "label": "AgentRepository", "file_type": "code", "source_file": "src/repository/memory/agent.go", "source_location": "L14"}, {"id": "rwmutex", "label": "RWMutex", "file_type": "code", "source_file": "src/repository/memory/agent.go", "source_location": "L15"}, {"id": "agent", "label": "Agent", "file_type": "code", "source_file": "src/repository/memory/agent.go", "source_location": "L16"}, {"id": "memory_agent_newagentrepository", "label": "NewAgentRepository()", "file_type": "code", "source_file": "src/repository/memory/agent.go", "source_location": "L19"}, {"id": "memory_agentrepository_create", "label": ".Create()", "file_type": "code", "source_file": "src/repository/memory/agent.go", "source_location": "L23"}, {"id": "context", "label": "Context", "file_type": "code", "source_file": "src/repository/memory/agent.go", "source_location": "L23"}, {"id": "memory_agentrepository_getbyid", "label": ".GetByID()", "file_type": "code", "source_file": "src/repository/memory/agent.go", "source_location": "L31"}, {"id": "memory_agentrepository_list", "label": ".List()", "file_type": "code", "source_file": "src/repository/memory/agent.go", "source_location": "L42"}, {"id": "memory_agentrepository_update", "label": ".Update()", "file_type": "code", "source_file": "src/repository/memory/agent.go", "source_location": "L67"}, {"id": "memory_agentrepository_delete", "label": ".Delete()", "file_type": "code", "source_file": "src/repository/memory/agent.go", "source_location": "L78"}], "edges": [{"source": "home_soic_project_spacetrek_src_repository_memory_agent_go", "target": "go_pkg_context", "relation": "imports_from", "confidence": "EXTRACTED", "source_file": "src/repository/memory/agent.go", "source_location": "L4", "weight": 1.0, "context": "import"}, {"source": "home_soic_project_spacetrek_src_repository_memory_agent_go", "target": "go_pkg_sort", "relation": "imports_from", "confidence": "EXTRACTED", "source_file": "src/repository/memory/agent.go", "source_location": "L5", "weight": 1.0, "context": "import"}, {"source": "home_soic_project_spacetrek_src_repository_memory_agent_go", "target": "go_pkg_sync", "relation": "imports_from", "confidence": "EXTRACTED", "source_file": "src/repository/memory/agent.go", "source_location": "L6", "weight": 1.0, "context": "import"}, {"source": "home_soic_project_spacetrek_src_repository_memory_agent_go", "target": "go_pkg_github_com_spacetrek_sh_spacetrek_pkg_exception", "relation": "imports_from", "confidence": "EXTRACTED", "source_file": "src/repository/memory/agent.go", "source_location": "L8", "weight": 1.0, "context": "import"}, {"source": "home_soic_project_spacetrek_src_repository_memory_agent_go", "target": "go_pkg_github_com_spacetrek_sh_spacetrek_src_core_domain_agent", "relation": "imports_from", "confidence": "EXTRACTED", "source_file": "src/repository/memory/agent.go", "source_location": "L9", "weight": 1.0, "context": "import"}, {"source": "home_soic_project_spacetrek_src_repository_memory_agent_go", "target": "memory_agentrepository", "relation": "contains", "confidence": "EXTRACTED", "source_file": "src/repository/memory/agent.go", "source_location": "L14", "weight": 1.0}, {"source": "memory_agentrepository", "target": "rwmutex", "relation": "references", "confidence": "EXTRACTED", "source_file": "src/repository/memory/agent.go", "source_location": "L15", "weight": 1.0, "context": "field"}, {"source": "memory_agentrepository", "target": "agent", "relation": "references", "confidence": "EXTRACTED", "source_file": "src/repository/memory/agent.go", "source_location": "L16", "weight": 1.0, "context": "field"}, {"source": "home_soic_project_spacetrek_src_repository_memory_agent_go", "target": "memory_agent_newagentrepository", "relation": "contains", "confidence": "EXTRACTED", "source_file": "src/repository/memory/agent.go", "source_location": "L19", "weight": 1.0}, {"source": "memory_agent_newagentrepository", "target": "memory_agentrepository", "relation": "references", "confidence": "EXTRACTED", "source_file": "src/repository/memory/agent.go", "source_location": "L19", "weight": 1.0, "context": "return_type"}, {"source": "memory_agentrepository", "target": "memory_agentrepository_create", "relation": "method", "confidence": "EXTRACTED", "source_file": "src/repository/memory/agent.go", "source_location": "L23", "weight": 1.0}, {"source": "memory_agentrepository_create", "target": "context", "relation": "references", "confidence": "EXTRACTED", "source_file": "src/repository/memory/agent.go", "source_location": "L23", "weight": 1.0, "context": "parameter_type"}, {"source": "memory_agentrepository_create", "target": "agent", "relation": "references", "confidence": "EXTRACTED", "source_file": "src/repository/memory/agent.go", "source_location": "L23", "weight": 1.0, "context": "parameter_type"}, {"source": "memory_agentrepository", "target": "memory_agentrepository_getbyid", "relation": "method", "confidence": "EXTRACTED", "source_file": "src/repository/memory/agent.go", "source_location": "L31", "weight": 1.0}, {"source": "memory_agentrepository_getbyid", "target": "context", "relation": "references", "confidence": "EXTRACTED", "source_file": "src/repository/memory/agent.go", "source_location": "L31", "weight": 1.0, "context": "parameter_type"}, {"source": "memory_agentrepository_getbyid", "target": "agent", "relation": "references", "confidence": "EXTRACTED", "source_file": "src/repository/memory/agent.go", "source_location": "L31", "weight": 1.0, "context": "return_type"}, {"source": "memory_agentrepository", "target": "memory_agentrepository_list", "relation": "method", "confidence": "EXTRACTED", "source_file": "src/repository/memory/agent.go", "source_location": "L42", "weight": 1.0}, {"source": "memory_agentrepository_list", "target": "context", "relation": "references", "confidence": "EXTRACTED", "source_file": "src/repository/memory/agent.go", "source_location": "L42", "weight": 1.0, "context": "parameter_type"}, {"source": "memory_agentrepository_list", "target": "agent", "relation": "references", "confidence": "EXTRACTED", "source_file": "src/repository/memory/agent.go", "source_location": "L42", "weight": 1.0, "context": "return_type"}, {"source": "memory_agentrepository", "target": "memory_agentrepository_update", "relation": "method", "confidence": "EXTRACTED", "source_file": "src/repository/memory/agent.go", "source_location": "L67", "weight": 1.0}, {"source": "memory_agentrepository_update", "target": "context", "relation": "references", "confidence": "EXTRACTED", "source_file": "src/repository/memory/agent.go", "source_location": "L67", "weight": 1.0, "context": "parameter_type"}, {"source": "memory_agentrepository_update", "target": "agent", "relation": "references", "confidence": "EXTRACTED", "source_file": "src/repository/memory/agent.go", "source_location": "L67", "weight": 1.0, "context": "parameter_type"}, {"source": "memory_agentrepository", "target": "memory_agentrepository_delete", "relation": "method", "confidence": "EXTRACTED", "source_file": "src/repository/memory/agent.go", "source_location": "L78", "weight": 1.0}, {"source": "memory_agentrepository_delete", "target": "context", "relation": "references", "confidence": "EXTRACTED", "source_file": "src/repository/memory/agent.go", "source_location": "L78", "weight": 1.0, "context": "parameter_type"}], "raw_calls": [{"caller_nid": "memory_agent_newagentrepository", "callee": "make", "is_member_call": false, "source_file": "/home/soic/project/spacetrek/src/repository/memory/agent.go", "source_location": "L20"}, {"caller_nid": "memory_agentrepository_create", "callee": "Lock", "is_member_call": true, "source_file": "/home/soic/project/spacetrek/src/repository/memory/agent.go", "source_location": "L24"}, {"caller_nid": "memory_agentrepository_create", "callee": "Unlock", "is_member_call": true, "source_file": "/home/soic/project/spacetrek/src/repository/memory/agent.go", "source_location": "L25"}, {"caller_nid": "memory_agentrepository_getbyid", "callee": "RLock", "is_member_call": true, "source_file": "/home/soic/project/spacetrek/src/repository/memory/agent.go", "source_location": "L32"}, {"caller_nid": "memory_agentrepository_getbyid", "callee": "RUnlock", "is_member_call": true, "source_file": "/home/soic/project/spacetrek/src/repository/memory/agent.go", "source_location": "L33"}, {"caller_nid": "memory_agentrepository_getbyid", "callee": "NotFound", "is_member_call": false, "source_file": "/home/soic/project/spacetrek/src/repository/memory/agent.go", "source_location": "L36"}, {"caller_nid": "memory_agentrepository_list", "callee": "RLock", "is_member_call": true, "source_file": "/home/soic/project/spacetrek/src/repository/memory/agent.go", "source_location": "L43"}, {"caller_nid": "memory_agentrepository_list", "callee": "RUnlock", "is_member_call": true, "source_file": "/home/soic/project/spacetrek/src/repository/memory/agent.go", "source_location": "L44"}, {"caller_nid": "memory_agentrepository_list", "callee": "make", "is_member_call": false, "source_file": "/home/soic/project/spacetrek/src/repository/memory/agent.go", "source_location": "L46"}, {"caller_nid": "memory_agentrepository_list", "callee": "append", "is_member_call": false, "source_file": "/home/soic/project/spacetrek/src/repository/memory/agent.go", "source_location": "L49"}, {"caller_nid": "memory_agentrepository_list", "callee": "Slice", "is_member_call": false, "source_file": "/home/soic/project/spacetrek/src/repository/memory/agent.go", "source_location": "L52"}, {"caller_nid": "memory_agentrepository_list", "callee": "After", "is_member_call": true, "source_file": "/home/soic/project/spacetrek/src/repository/memory/agent.go", "source_location": "L53"}, {"caller_nid": "memory_agentrepository_list", "callee": "int64", "is_member_call": false, "source_file": "/home/soic/project/spacetrek/src/repository/memory/agent.go", "source_location": "L56"}, {"caller_nid": "memory_agentrepository_update", "callee": "Lock", "is_member_call": true, "source_file": "/home/soic/project/spacetrek/src/repository/memory/agent.go", "source_location": "L68"}, {"caller_nid": "memory_agentrepository_update", "callee": "Unlock", "is_member_call": true, "source_file": "/home/soic/project/spacetrek/src/repository/memory/agent.go", "source_location": "L69"}, {"caller_nid": "memory_agentrepository_update", "callee": "NotFound", "is_member_call": false, "source_file": "/home/soic/project/spacetrek/src/repository/memory/agent.go", "source_location": "L71"}, {"caller_nid": "memory_agentrepository_delete", "callee": "Lock", "is_member_call": true, "source_file": "/home/soic/project/spacetrek/src/repository/memory/agent.go", "source_location": "L79"}, {"caller_nid": "memory_agentrepository_delete", "callee": "Unlock", "is_member_call": true, "source_file": "/home/soic/project/spacetrek/src/repository/memory/agent.go", "source_location": "L80"}, {"caller_nid": "memory_agentrepository_delete", "callee": "NotFound", "is_member_call": false, "source_file": "/home/soic/project/spacetrek/src/repository/memory/agent.go", "source_location": "L82"}, {"caller_nid": "memory_agentrepository_delete", "callee": "delete", "is_member_call": false, "source_file": "/home/soic/project/spacetrek/src/repository/memory/agent.go", "source_location": "L84"}]}